README.md
setup.cfg
setup.py
dist_ktsvl/Binomialdistribution.py
dist_ktsvl/Gaussiandistribution.py
dist_ktsvl/Generaldistribution.py
dist_ktsvl/__init__.py
dist_ktsvl.egg-info/PKG-INFO
dist_ktsvl.egg-info/SOURCES.txt
dist_ktsvl.egg-info/dependency_links.txt
dist_ktsvl.egg-info/not-zip-safe
dist_ktsvl.egg-info/top_level.txt